named_ids/__init__.py
named_ids/assets/adjectives.txt
named_ids/assets/adverbs.txt
named_ids/assets/nouns.txt
named_ids/assets/verbs.txt
named_ids-0.1.0.dist-info/LICENSE
named_ids-0.1.0.dist-info/METADATA
named_ids-0.1.0.dist-info/WHEEL
named_ids-0.1.0.dist-info/top_level.txt
named_ids-0.1.0.dist-info/RECORD
