Metadata-Version: 2.2
Name: named_ids
Version: 0.1.0
Summary: Human-readable unique identifiers
Home-page: https://github.com/gergopool/named_ids
Author: Gergely Papp
Author-email: Gergely Papp <gergopool@gmail.com>
License: MIT
Project-URL: Homepage, https://github.com/gergopool/named_ids
Project-URL: Bug Tracker, https://github.com/gergopool/named_ids/issues
Classifier: Programming Language :: Python :: 3
Classifier: License :: OSI Approved :: MIT License
Classifier: Operating System :: OS Independent
Requires-Python: >=3.6
License-File: LICENSE
Dynamic: author
Dynamic: home-page
Dynamic: requires-python
